.coveragerc
LICENSE
MANIFEST
MANIFEST.in
README.md
config.py
requirements.txt
run.py
setup.cfg
setup.py
tox.ini
beacons/.DS_Store
beacons/__init__.py
beacons/__init__.pyc
beacons/portal/.DS_Store
beacons/portal/__init__.py
beacons/portal/__init__.pyc
beacons/portal/controller/.DS_Store
beacons/portal/controller/.controller.py.swp
beacons/portal/controller/__init__.py
beacons/portal/controller/__init__.pyc
beacons/portal/controller/controller.py
beacons/portal/controller/controller.pyc
beacons/portal/helper/.DS_Store
beacons/portal/helper/__init__.py
beacons/portal/helper/__init__.pyc
beacons/portal/helper/beacon_helper.py
beacons/portal/helper/beacon_helper.pyc
beacons/portal/helper/url_helper.py
beacons/portal/helper/url_helper.pyc
beacons/portal/models/__init__.py
beacons/portal/models/__init__.pyc
beacons/portal/models/beacons.py
beacons/portal/models/beacons.pyc
beacons/portal/models/eddystone_beacon.py
beacons/portal/models/eddystone_beacon.pyc
beacons/portal/models/header.py
beacons/portal/models/header.pyc
beacons/portal/models/ibeacon.py
beacons/portal/models/ibeacon.pyc
beacons/portal/view/.error_handler.py.swp
beacons/portal/view/.views.py.swp
beacons/portal/view/__init__.py
beacons/portal/view/__init__.pyc
beacons/portal/view/error_handler.py
beacons/portal/view/error_handler.pyc
beacons/portal/view/views.py
beacons/portal/view/views.pyc
beacons/static/css/base.css
beacons/static/js/attachment.js
beacons/static/js/base.js
beacons/static/js/editBeacon.js
beacons/static/js/register.js
beacons/static/js/view-attachments.js
beacons/templates/_formhelpers.jinja
beacons/templates/attachment.jinja
beacons/templates/attachment_status.jinja
beacons/templates/base.jinja
beacons/templates/beacons.jinja
beacons/templates/edit_beacon.jinja
beacons/templates/edit_beacon_status.jinja
beacons/templates/error.jinja
beacons/templates/estimote_details.jinja
beacons/templates/register.jinja
beacons/templates/registration_status.jinja
beacons/templates/unregister.jinja
my_beacon_manager.egg-info/PKG-INFO
my_beacon_manager.egg-info/SOURCES.txt
my_beacon_manager.egg-info/dependency_links.txt
my_beacon_manager.egg-info/not-zip-safe
my_beacon_manager.egg-info/top_level.txt
