Metadata-Version: 1.1
Name: my-beacon-manager
Version: 2.5
Summary: Beacon Manager
Home-page: https://www.github.com/rajatguptarg/beacons
Author: Rajat Gupta
Author-email: rajat.gupta712@gmail.com
License: MIT
Platform: UNKNOWN
Classifier: Development Status :: 1 - Planning
Classifier: Environment :: Plugins
Classifier: Intended Audience :: Developers
Classifier: License :: OSI Approved :: MIT License
Classifier: Natural Language :: English
Classifier: Operating System :: OS Independent
Classifier: Programming Language :: Python
Classifier: Framework :: Flask
Classifier: Topic :: Office/Business
